<annotation>
  <folder>train</folder>
  <filename>IMG_9489_948.jpg</filename>
  <path>/home/u/PycharmProjects/flyprepare/images/train/IMG_9489_948.jpg</path>
  <source>
    <database>Unknown</database>
  </source>
  <size>
    <width>864</width>
    <height>864</height>
    <depth>3</depth>
  </size>
  <segmented>0</segmented>
  <object>
    <name>larve</name>
    <pose>Unspecified</pose>
    <truncated>0</truncated>
    <difficult>0</difficult>
    <bndbox>
      <xmin>726</xmin>
      <ymin>15</ymin>
      <xmax>808</xmax>
      <ymax>135</ymax>
    </bndbox>
  </object>
  <object>
    <name>larve</name>
    <pose>Unspecified</pose>
    <truncated>0</truncated>
    <difficult>0</difficult>
    <bndbox>
      <xmin>614</xmin>
      <ymin>76</ymin>
      <xmax>728</xmax>
      <ymax>164</ymax>
    </bndbox>
  </object>
  <object>
    <name>larve</name>
    <pose>Unspecified</pose>
    <truncated>0</truncated>
    <difficult>0</difficult>
    <bndbox>
      <xmin>357</xmin>
      <ymin>35</ymin>
      <xmax>484</xmax>
      <ymax>110</ymax>
    </bndbox>
  </object>
  <object>
    <name>larve</name>
    <pose>Unspecified</pose>
    <truncated>0</truncated>
    <difficult>0</difficult>
    <bndbox>
      <xmin>247</xmin>
      <ymin>17</ymin>
      <xmax>329</xmax>
      <ymax>139</ymax>
    </bndbox>
  </object>
  <object>
    <name>larve</name>
    <pose>Unspecified</pose>
    <truncated>0</truncated>
    <difficult>0</difficult>
    <bndbox>
      <xmin>204</xmin>
      <ymin>212</ymin>
      <xmax>363</xmax>
      <ymax>276</ymax>
    </bndbox>
  </object>
  <object>
    <name>larve</name>
    <pose>Unspecified</pose>
    <truncated>0</truncated>
    <difficult>0</difficult>
    <bndbox>
      <xmin>551</xmin>
      <ymin>172</ymin>
      <xmax>755</xmax>
      <ymax>243</ymax>
    </bndbox>
  </object>
  <object>
    <name>larve</name>
    <pose>Unspecified</pose>
    <truncated>0</truncated>
    <difficult>0</difficult>
    <bndbox>
      <xmin>633</xmin>
      <ymin>233</ymin>
      <xmax>751</xmax>
      <ymax>292</ymax>
    </bndbox>
  </object>
  <object>
    <name>larve</name>
    <pose>Unspecified</pose>
    <truncated>0</truncated>
    <difficult>0</difficult>
    <bndbox>
      <xmin>682</xmin>
      <ymin>325</ymin>
      <xmax>814</xmax>
      <ymax>459</ymax>
    </bndbox>
  </object>
  <object>
    <name>larve</name>
    <pose>Unspecified</pose>
    <truncated>0</truncated>
    <difficult>0</difficult>
    <bndbox>
      <xmin>602</xmin>
      <ymin>264</ymin>
      <xmax>673</xmax>
      <ymax>410</ymax>
    </bndbox>
  </object>
  <object>
    <name>larve</name>
    <pose>Unspecified</pose>
    <truncated>0</truncated>
    <difficult>0</difficult>
    <bndbox>
      <xmin>561</xmin>
      <ymin>274</ymin>
      <xmax>628</xmax>
      <ymax>412</ymax>
    </bndbox>
  </object>
  <object>
    <name>larve</name>
    <pose>Unspecified</pose>
    <truncated>0</truncated>
    <difficult>0</difficult>
    <bndbox>
      <xmin>518</xmin>
      <ymin>274</ymin>
      <xmax>557</xmax>
      <ymax>425</ymax>
    </bndbox>
  </object>
  <object>
    <name>larve</name>
    <pose>Unspecified</pose>
    <truncated>0</truncated>
    <difficult>0</difficult>
    <bndbox>
      <xmin>453</xmin>
      <ymin>184</ymin>
      <xmax>526</xmax>
      <ymax>300</ymax>
    </bndbox>
  </object>
  <object>
    <name>larve</name>
    <pose>Unspecified</pose>
    <truncated>0</truncated>
    <difficult>0</difficult>
    <bndbox>
      <xmin>337</xmin>
      <ymin>219</ymin>
      <xmax>463</xmax>
      <ymax>394</ymax>
    </bndbox>
  </object>
  <object>
    <name>larve</name>
    <pose>Unspecified</pose>
    <truncated>0</truncated>
    <difficult>0</difficult>
    <bndbox>
      <xmin>251</xmin>
      <ymin>312</ymin>
      <xmax>422</xmax>
      <ymax>382</ymax>
    </bndbox>
  </object>
  <object>
    <name>larve</name>
    <pose>Unspecified</pose>
    <truncated>0</truncated>
    <difficult>0</difficult>
    <bndbox>
      <xmin>220</xmin>
      <ymin>382</ymin>
      <xmax>331</xmax>
      <ymax>455</ymax>
    </bndbox>
  </object>
  <object>
    <name>larve</name>
    <pose>Unspecified</pose>
    <truncated>0</truncated>
    <difficult>0</difficult>
    <bndbox>
      <xmin>490</xmin>
      <ymin>435</ymin>
      <xmax>682</xmax>
      <ymax>545</ymax>
    </bndbox>
  </object>
  <object>
    <name>larve</name>
    <pose>Unspecified</pose>
    <truncated>0</truncated>
    <difficult>0</difficult>
    <bndbox>
      <xmin>763</xmin>
      <ymin>553</ymin>
      <xmax>829</xmax>
      <ymax>651</ymax>
    </bndbox>
  </object>
  <object>
    <name>larve</name>
    <pose>Unspecified</pose>
    <truncated>0</truncated>
    <difficult>0</difficult>
    <bndbox>
      <xmin>678</xmin>
      <ymin>572</ymin>
      <xmax>751</xmax>
      <ymax>759</ymax>
    </bndbox>
  </object>
  <object>
    <name>larve</name>
    <pose>Unspecified</pose>
    <truncated>0</truncated>
    <difficult>0</difficult>
    <bndbox>
      <xmin>537</xmin>
      <ymin>553</ymin>
      <xmax>665</xmax>
      <ymax>590</ymax>
    </bndbox>
  </object>
  <object>
    <name>larve</name>
    <pose>Unspecified</pose>
    <truncated>0</truncated>
    <difficult>0</difficult>
    <bndbox>
      <xmin>298</xmin>
      <ymin>570</ymin>
      <xmax>467</xmax>
      <ymax>690</ymax>
    </bndbox>
  </object>
  <object>
    <name>larve</name>
    <pose>Unspecified</pose>
    <truncated>0</truncated>
    <difficult>0</difficult>
    <bndbox>
      <xmin>420</xmin>
      <ymin>627</ymin>
      <xmax>629</xmax>
      <ymax>739</ymax>
    </bndbox>
  </object>
  <object>
    <name>larve</name>
    <pose>Unspecified</pose>
    <truncated>0</truncated>
    <difficult>0</difficult>
    <bndbox>
      <xmin>551</xmin>
      <ymin>631</ymin>
      <xmax>678</xmax>
      <ymax>741</ymax>
    </bndbox>
  </object>
  <object>
    <name>larve</name>
    <pose>Unspecified</pose>
    <truncated>0</truncated>
    <difficult>0</difficult>
    <bndbox>
      <xmin>680</xmin>
      <ymin>668</ymin>
      <xmax>824</xmax>
      <ymax>851</ymax>
    </bndbox>
  </object>
  <object>
    <name>larve</name>
    <pose>Unspecified</pose>
    <truncated>0</truncated>
    <difficult>0</difficult>
    <bndbox>
      <xmin>96</xmin>
      <ymin>580</ymin>
      <xmax>204</xmax>
      <ymax>739</ymax>
    </bndbox>
  </object>
  <object>
    <name>larve</name>
    <pose>Unspecified</pose>
    <truncated>0</truncated>
    <difficult>0</difficult>
    <bndbox>
      <xmin>31</xmin>
      <ymin>406</ymin>
      <xmax>192</xmax>
      <ymax>582</ymax>
    </bndbox>
  </object>
  <object>
    <name>larve</name>
    <pose>Unspecified</pose>
    <truncated>0</truncated>
    <difficult>0</difficult>
    <bndbox>
      <xmin>94</xmin>
      <ymin>266</ymin>
      <xmax>249</xmax>
      <ymax>323</ymax>
    </bndbox>
  </object>
</annotation>
