<annotation>
	<folder>train</folder>
	<filename>IMG_9354_62.jpg</filename>
	<path>/home/u/PycharmProjects/flyprepare/images/train/IMG_9354_62.jpg</path>
	<source>
		<database>Unknown</database>
	</source>
	<size>
		<width>648</width>
		<height>432</height>
		<depth>3</depth>
	</size>
	<segmented>0</segmented>
	<object>
		<name>larvae</name>
		<pose>Unspecified</pose>
		<truncated>0</truncated>
		<difficult>0</difficult>
		<bndbox>
			<xmin>324</xmin>
			<ymin>192</ymin>
			<xmax>437</xmax>
			<ymax>365</ymax>
		</bndbox>
	</object>
	<object>
		<name>larvae</name>
		<pose>Unspecified</pose>
		<truncated>0</truncated>
		<difficult>0</difficult>
		<bndbox>
			<xmin>420</xmin>
			<ymin>228</ymin>
			<xmax>510</xmax>
			<ymax>366</ymax>
		</bndbox>
	</object>
	<object>
		<name>larvae</name>
		<pose>Unspecified</pose>
		<truncated>1</truncated>
		<difficult>0</difficult>
		<bndbox>
			<xmin>1</xmin>
			<ymin>20</ymin>
			<xmax>147</xmax>
			<ymax>94</ymax>
		</bndbox>
	</object>
	<object>
		<name>larvae</name>
		<pose>Unspecified</pose>
		<truncated>0</truncated>
		<difficult>0</difficult>
		<bndbox>
			<xmin>50</xmin>
			<ymin>240</ymin>
			<xmax>228</xmax>
			<ymax>415</ymax>
		</bndbox>
	</object>
</annotation>
